apparun/__init__.py
apparun/core.py
apparun/exceptions.py
apparun/expressions.py
apparun/impact_methods.py
apparun/impact_model.py
apparun/impact_tree.py
apparun/logger.py
apparun/parameters.py
apparun/results.py
apparun/score.py
apparun/tree_node.py
apparun/api/__init__.py
apparun/api/app.py
apparun/cli/__init__.py
apparun/cli/main.py
apparun/gui/__init__.py
apparun/gui/modules.py
apparun/gui/panels/__init__.py
apparun/gui/panels/base.py
apparun/gui/panels/output_dynamic.py
apparun/gui/panels/output_static.py
apparun/resources/pef30/normalisation_factor.csv
apparun/resources/pef30/weighting_factor.csv
apparun/resources/pef31/normalisation_factor.csv
apparun/resources/pef31/weighting_factor.csv
apparun-0.4.0.dist-info/METADATA
apparun-0.4.0.dist-info/WHEEL
apparun-0.4.0.dist-info/entry_points.txt
apparun-0.4.0.dist-info/licenses/LICENSE.md
apparun-0.4.0.dist-info/RECORD
