Metadata-Version: 2.4
Name: apparun
Version: 0.4.0
Summary: Appa Run is a package to execute impact models produced by Appa Build
Project-URL: Source, https://github.com/appalca/apparun/
Author-email: Maxime Peralta <maxime.peralta@cea.fr>
Maintainer-email: Maxime Peralta <maxime.peralta@cea.fr>
License: # GNU LESSER GENERAL PUBLIC LICENSE
License-File: LICENSE.md
Keywords: ecodesign,life cycle assessment
Classifier: Intended Audience :: Developers
Classifier: Intended Audience :: Manufacturing
Classifier: Intended Audience :: Science/Research
Classifier: Programming Language :: Python
Classifier: Programming Language :: Python :: 3
Classifier: Topic :: Scientific/Engineering
Requires-Python: <3.12,>=3.11
Requires-Dist: aenum
Requires-Dist: click==8.1.8
Requires-Dist: fastapi==0.120.1
Requires-Dist: hatchling==1.27.0
Requires-Dist: kaleido==1.2.0
Requires-Dist: networkx==3.4.2
Requires-Dist: numpy==1.26.4
Requires-Dist: pandas==2.3.3
Requires-Dist: plotly==6.3.1
Requires-Dist: pydantic
Requires-Dist: pytest==8.4.2
Requires-Dist: pyyaml==6.0.1
Requires-Dist: salib==1.5.1
Requires-Dist: scipy==1.16.2
Requires-Dist: streamlit==1.52.2
Requires-Dist: sympy==1.14.0
Requires-Dist: typer==0.15.1
Requires-Dist: uvicorn[standard]
